find_reference_genomes/__init__.py
find_reference_genomes/command_line.py
find_reference_genomes/genome.py
find_reference_genomes/lineage.py
find_reference_genomes/main.py
find_reference_genomes-1.1.2.dist-info/licenses/LICENSE.md
find_reference_genomes-1.1.2.dist-info/METADATA
find_reference_genomes-1.1.2.dist-info/WHEEL
find_reference_genomes-1.1.2.dist-info/entry_points.txt
find_reference_genomes-1.1.2.dist-info/top_level.txt
find_reference_genomes-1.1.2.dist-info/RECORD
