Metadata-Version: 2.4
Name: find_reference_genomes
Version: 1.1.2
Summary: Easily find and download reference genomes stored at NCBI
Author: bistace
Author-email: bistace@genoscope.cns.fr
Classifier: Programming Language :: Python :: 3
Classifier: License :: OSI Approved :: CEA CNRS Inria Logiciel Libre License, version 2.1 (CeCILL-2.1)
Classifier: Operating System :: OS Independent
License-File: LICENSE.md
Requires-Dist: pytest
Requires-Dist: requests
Dynamic: author
Dynamic: author-email
Dynamic: classifier
Dynamic: description
Dynamic: description-content-type
Dynamic: license-file
Dynamic: requires-dist
Dynamic: summary
